MANIFEST.in
README.md
pyproject.toml
requirements.txt
setup.py
test_requirements.txt
version.txt
./__init__.py
./auth.py
./backend.py
./chaiverse_secrets.py
./chaiverse_server.py
./chat.py
./cli.py
./config.py
./errors.py
./fastapi_instrumentator.py
./feed.py
./formatters.py
./http_client.py
./leaderboard_cli.py
./logging.py
./models.py
./submit.py
./utils.py
./cli_utils/login_cli.py
./database/__init__.py
./database/firebase_database.py
./database/inferno_database_adapter.py
./database/mock_database.py
./database/redis_database.py
./lib/__init__.py
./lib/async_tools.py
./lib/dataframe_tools.py
./lib/date_tools.py
./lib/dict_tools.py
./lib/elo.py
./lib/exception_logger.py
./lib/func.py
./lib/math_tools.py
./lib/now.py
./lib/pydantic_tools.py
./lib/shutdown_handler.py
./lib/timeout_lock.py
./resources/bot_config/blade.json
./resources/bot_config/captain_wyatt.json
./resources/bot_config/coffee_shop_girl.json
./resources/bot_config/filbert.json
./resources/bot_config/leo.json
./resources/bot_config/levi.json
./resources/bot_config/mr_wilson.json
./resources/bot_config/nerd_girl.json
./resources/bot_config/scaramouche.json
./resources/bot_config/story_teller.json
./resources/bot_config/vampire_queen.json
./resources/bot_config/wednesday_addams.json
./schemas/__init__.py
./schemas/date_range_schema.py
./schemas/leaderboard_row_schema.py
./schemas/leaderboard_schema.py
./schemas/preference_summary_schema.py
chaiverse.egg-info/PKG-INFO
chaiverse.egg-info/SOURCES.txt
chaiverse.egg-info/dependency_links.txt
chaiverse.egg-info/entry_points.txt
chaiverse.egg-info/not-zip-safe
chaiverse.egg-info/requires.txt
chaiverse.egg-info/top_level.txt