Metadata-Version: 2.1
Name: chaiverse
Version: 1.29.6
Summary: Chaiverse
Home-page: https://www.chaiverse.com
Author: Chai Research Corp.
Author-email: hello@chai-research.com
License: MIT
Platform: UNKNOWN
